oas_cli/__init__.py
oas_cli/banner.py
oas_cli/code_generation.py
oas_cli/data_preparation.py
oas_cli/generators.py
oas_cli/main.py
oas_cli/tools.py
oas_cli/utils.py
oas_cli/validators.py
oas_cli/schemas/oas-schema.json
oas_cli/templates/GITHUB_ACTIONS_AGENTS_README.md
oas_cli/templates/SECURITY_TEMPLATES.md
oas_cli/templates/__init__.py
oas_cli/templates/agent.py.j2
oas_cli/templates/cortex-intelligence-agent.yaml
oas_cli/templates/github-actions-error-analyzer.yaml
oas_cli/templates/github-actions-error-collector.yaml
oas_cli/templates/github-actions-error-workflow.yaml
oas_cli/templates/github-actions-sample-data.json
oas_cli/templates/grok-security-analyzer.yaml
oas_cli/templates/minimal-agent-tool-usage.yaml
oas_cli/templates/minimal-agent.yaml
oas_cli/templates/minimal-multi-task-agent.yaml
oas_cli/templates/security-incident-responder.yaml
oas_cli/templates/security-risk-assessor.yaml
oas_cli/templates/security-threat-analyzer.yaml
oas_cli/templates/task_function.py.j2
open_agent_spec-1.2.0.dist-info/METADATA
open_agent_spec-1.2.0.dist-info/WHEEL
open_agent_spec-1.2.0.dist-info/entry_points.txt
open_agent_spec-1.2.0.dist-info/licenses/LICENSE
open_agent_spec-1.2.0.dist-info/licenses/NOTICE
open_agent_spec-1.2.0.dist-info/RECORD
