Metadata-Version: 2.4
Name: open-agent-spec
Version: 1.2.0
Summary: Open Agent Spec CLI for bootstrapping AI agent projects
Author-email: Andrew Whitehouse <andrewswhitehouse@gmail.com>
License: AGPL-3.0-only
License-File: LICENSE
License-File: NOTICE
Requires-Python: >=3.10
Requires-Dist: anthropic>=0.3.0
Requires-Dist: behavioural-contracts==0.1.2
Requires-Dist: dacp>=0.3.3
Requires-Dist: jinja2>=3.0.0
Requires-Dist: jsonschema>=4.0.0
Requires-Dist: openai>=1.0.0
Requires-Dist: python-dotenv>=0.19.0
Requires-Dist: pyyaml
Requires-Dist: rich
Requires-Dist: setuptools>=69.0.0
Requires-Dist: tomli>=1.0.0; python_version < '3.11'
Requires-Dist: typer[all]>=0.9.0
Provides-Extra: dev
Requires-Dist: allure-pytest>=2.0.0; extra == 'dev'
Requires-Dist: build>=1.0.0; extra == 'dev'
Requires-Dist: isort>=5.0.0; extra == 'dev'
Requires-Dist: mypy>=1.0.0; extra == 'dev'
Requires-Dist: pre-commit>=3.0.0; extra == 'dev'
Requires-Dist: pytest-cov>=4.0.0; extra == 'dev'
Requires-Dist: pytest-html>=3.0.0; extra == 'dev'
Requires-Dist: pytest-xdist>=3.0.0; extra == 'dev'
Requires-Dist: pytest>=7.0.0; extra == 'dev'
Requires-Dist: ruff>=0.1.0; extra == 'dev'
Requires-Dist: twine>=4.0.0; extra == 'dev'
Requires-Dist: types-jsonschema; extra == 'dev'
Requires-Dist: types-pyyaml>=6.0.0; extra == 'dev'
Requires-Dist: types-setuptools>=69.0.0; extra == 'dev'
Requires-Dist: types-toml>=0.10.0; extra == 'dev'
